drafttopic/__init__.py
drafttopic/about.py
drafttopic/drafttopic.py
drafttopic/feature_lists/__init__.py
drafttopic/feature_lists/arwiki.py
drafttopic/feature_lists/cswiki.py
drafttopic/feature_lists/enwiki.py
drafttopic/feature_lists/euwiki.py
drafttopic/feature_lists/huwiki.py
drafttopic/feature_lists/hywiki.py
drafttopic/feature_lists/kowiki.py
drafttopic/feature_lists/srwiki.py
drafttopic/feature_lists/ukwiki.py
drafttopic/feature_lists/viwiki.py
drafttopic/feature_lists/wikidata.py
drafttopic/utilities/__init__.py
drafttopic/utilities/add_central_africa.py
drafttopic/utilities/balance_sample.py
drafttopic/utilities/extract_from_text.py
drafttopic/utilities/fetch_article_text.py
drafttopic/utilities/fetch_draft_text.py
drafttopic/utilities/taxo_label.py
drafttopic/utilities/write_labels.py
drafttopic/utilities/tests/__init__.py
drafttopic/utilities/tests/test_extract_from_text.py
drafttopic/utilities/tests/test_write_labels.py
drafttopic-0.4.1.dist-info/LICENSE
drafttopic-0.4.1.dist-info/METADATA
drafttopic-0.4.1.dist-info/WHEEL
drafttopic-0.4.1.dist-info/entry_points.txt
drafttopic-0.4.1.dist-info/top_level.txt
drafttopic-0.4.1.dist-info/RECORD
