Metadata-Version: 2.1
Name: drafttopic
Version: 0.4.1
Summary: A library for automatic detection of topics of new drafts on Wikipedia based on WikiProjects.
Home-page: https://github.com/wikimedia/drafttopic
Author: Aaron Halfaker, Sumit Asthana
Author-email: ahalfaker@wikimedia.org, asthana.sumit23@gmail.com
License: MIT
Classifier: Development Status :: 4 - Beta
Classifier: Topic :: Software Development :: Libraries :: Python Modules
Classifier: Programming Language :: Python
Classifier: Programming Language :: Python :: 3
Classifier: Intended Audience :: Developers
Classifier: License :: OSI Approved :: MIT License
Classifier: Operating System :: OS Independent
Classifier: Topic :: Utilities
Classifier: Topic :: Scientific/Engineering
License-File: LICENSE
